foliant/preprocessors/dbdoc/__init__.py
foliant/preprocessors/dbdoc/dbdoc.py
foliant/preprocessors/dbdoc/base/__init__.py
foliant/preprocessors/dbdoc/base/main.py
foliant/preprocessors/dbdoc/mssql/__init__.py
foliant/preprocessors/dbdoc/mssql/main.py
foliant/preprocessors/dbdoc/mssql/queries.py
foliant/preprocessors/dbdoc/mssql/templates/doc.j2
foliant/preprocessors/dbdoc/mssql/templates/scheme.j2
foliant/preprocessors/dbdoc/mysql/__init__.py
foliant/preprocessors/dbdoc/mysql/main.py
foliant/preprocessors/dbdoc/mysql/queries.py
foliant/preprocessors/dbdoc/mysql/templates/doc.j2
foliant/preprocessors/dbdoc/mysql/templates/scheme.j2
foliant/preprocessors/dbdoc/oracle/__init__.py
foliant/preprocessors/dbdoc/oracle/main.py
foliant/preprocessors/dbdoc/oracle/queries.py
foliant/preprocessors/dbdoc/oracle/templates/doc.j2
foliant/preprocessors/dbdoc/oracle/templates/scheme.j2
foliant/preprocessors/dbdoc/pgsql/__init__.py
foliant/preprocessors/dbdoc/pgsql/main.py
foliant/preprocessors/dbdoc/pgsql/queries.py
foliant/preprocessors/dbdoc/pgsql/templates/doc.j2
foliant/preprocessors/dbdoc/pgsql/templates/scheme.j2
foliantcontrib_dbdoc-0.1.10.dist-info/licenses/LICENSE
tests/__init__.py
tests/test_mysql_basic.py
tests/test_pgsql_basic.py
foliantcontrib_dbdoc-0.1.10.dist-info/METADATA
foliantcontrib_dbdoc-0.1.10.dist-info/WHEEL
foliantcontrib_dbdoc-0.1.10.dist-info/top_level.txt
foliantcontrib_dbdoc-0.1.10.dist-info/RECORD
